CHANGES.txt
LICENSE.txt
MANIFEST.in
README.md
setup.py
bluestocking/__init__.py
bluestocking/doxament.py
bluestocking/factchecker.py
bluestocking/parse.py
bluestocking/tests.py
bluestocking/wiki2plain.py
bluestocking/wikipedia.py
bluestocking.egg-info/PKG-INFO
bluestocking.egg-info/SOURCES.txt
bluestocking.egg-info/dependency_links.txt
bluestocking.egg-info/requires.txt
bluestocking.egg-info/top_level.txt