Metadata-Version: 1.0
Name: bluestocking
Version: 0.1.1
Summary: An information extraction toolkit built on top of NLTK.
Home-page: UNKNOWN
Author: UNKNOWN
Author-email: bluestocking-dev@googlegroups.com
License: GPL
Platform: UNKNOWN
